{"data": {"id": "1401670258121973767", "entities": {"annotations": [{"start": 76, "end": 88, "probability": 0.5893, "type": "Organization", "normalized_text": "Partido Verde"}], "urls": [{"start": 108, "end": 131, "url": "https://t.co/4Nw6PQrGgH", "expanded_url": "https://twitter.com/camilablacksun/status/1401457598520606722/photo/1", "display_url": "pic.twitter.com/4Nw6PQrGgH"}, {"start": 108, "end": 131, "url": "https://t.co/4Nw6PQrGgH", "expanded_url": "https://twitter.com/camilablacksun/status/1401457598520606722/photo/1", "display_url": "pic.twitter.com/4Nw6PQrGgH"}, {"start": 108, "end": 131, "url": "https://t.co/4Nw6PQrGgH", "expanded_url": "https://twitter.com/camilablacksun/status/1401457598520606722/photo/1", "display_url": "pic.twitter.com/4Nw6PQrGgH"}, {"start": 108, "end": 131, "url": "https://t.co/4Nw6PQrGgH", "expanded_url": "https://twitter.com/camilablacksun/status/1401457598520606722/photo/1", "display_url": "pic.twitter.com/4Nw6PQrGgH"}], "hashtags": [{"start": 92, "end": 107, "tag": "Elecciones2021"}], "mentions": [{"start": 3, "end": 17, "username": "babywithagunx"}]}, "referenced_tweets": [{"type": "retweeted", "id": "1401457598520606722"}], "attachments": {"media_keys": ["3_1401457591465570309", "3_1401457591469764608", "3_1401457591474036737", "3_1401457591465615363"]}, "public_metrics": {"retweet_count": 3548, "reply_count": 0, "like_count": 0, "quote_count": 0}, "author_id": "97388612", "created_at": "2021-06-06T22:40:05.000Z", "source": "Twitter for iPhone", "text": "RT @babywithagunx: Abro hilo con todos los qleros que le aceptaron su \ud83d\udca9 al Partido Verde. \n\n#Elecciones2021 https://t.co/4Nw6PQrGgH"}, "includes": {"users": [{"name": "ISAI ALFONSO \u2693\ufe0f", "public_metrics": {"followers_count": 1832, "following_count": 1879, "tweet_count": 12913, "listed_count": 9}, "id": "97388612", "location": "Round the Surrealism", "description": "\u0395\u03b3\u03ce \u03b5\u03af\u03bc\u03b1\u03b9: Abogado Publicitario / Gestor / Fot\u00f3grafo / Jugador de Volley / 27 a\u00f1os / \u2693 INSTAGRAM & TikTok: @Lostmac", "username": "Lostmac", "protected": false, "created_at": "2009-12-17T07:21:05.000Z", "verified": false}]}, "matching_rules": [{"id": 1401668264036548615, "tag": "Nuevo Le\u00f3n"}, {"id": 1401668264036548614, "tag": "Monterrey"}]}