{"data": {"id": "1401691979273080834", "referenced_tweets": [{"type": "replied_to", "id": "1401678328575180804"}], "public_metrics": {"retweet_count": 0, "reply_count": 0, "like_count": 0, "quote_count": 0}, "in_reply_to_user_id": "1465835347", "author_id": "214749115", "created_at": "2021-06-07T00:06:24.000Z", "source": "Twitter for Android", "text": "@emalaris @LCUgalde @INEMexico Cierto \ud83d\ude02\ud83d\ude02\ud83d\ude02", "entities": {"mentions": [{"start": 0, "end": 9, "username": "emalaris"}, {"start": 10, "end": 19, "username": "LCUgalde"}, {"start": 20, "end": 30, "username": "INEMexico"}]}}, "includes": {"users": [{"name": "Paos", "public_metrics": {"followers_count": 103, "following_count": 779, "tweet_count": 3093, "listed_count": 3}, "id": "214749115", "description": "Tecnolog\u00eda, deportes& \ud83c\udfce\ufe0f, fotograf\u00eda, moda&deco, doblaje y locuci\u00f3n...viviendo de emoci\u00f3n!", "username": "superpaorj", "protected": false, "created_at": "2010-11-12T03:52:25.000Z", "verified": false}]}, "matching_rules": [{"id": 1401668264036548616, "tag": "INE - Monterrey"}, {"id": 1401668264036548619, "tag": "INE - Nuevo Le\u00f3n"}]}