{"data": {"id": "1401693058404544516", "referenced_tweets": [{"type": "quoted", "id": "1401617492951379969"}], "entities": {"urls": [{"start": 252, "end": 275, "url": "https://t.co/hRRAbWwqjD", "expanded_url": "https://twitter.com/TheNCSmaster/status/1401617492951379969", "display_url": "twitter.com/TheNCSmaster/s\u2026"}], "hashtags": [{"start": 198, "end": 205, "tag": "E32021"}, {"start": 207, "end": 222, "tag": "NintendoSwitch"}, {"start": 224, "end": 239, "tag": "hopesanddreams"}]}, "public_metrics": {"retweet_count": 0, "reply_count": 0, "like_count": 0, "quote_count": 0}, "author_id": "1400682891512729603", "created_at": "2021-06-07T00:10:41.000Z", "source": "Twitter Web App", "context_annotations": [{"domain": {"id": "45", "name": "Brand Vertical", "description": "Top level entities that describe a Brands industry"}, "entity": {"id": "781974597310615553", "name": "Entertainment"}}, {"domain": {"id": "46", "name": "Brand Category", "description": "Categories within Brand Verticals that narrow down the scope of Brands"}, "entity": {"id": "781974597218340864", "name": "Video Games"}}, {"domain": {"id": "47", "name": "Brand", "description": "Brands and Companies"}, "entity": {"id": "10026713294", "name": "Nintendo"}}, {"domain": {"id": "78", "name": "Video Game Publisher", "description": "A Video Game Publisher like 'Activision'"}, "entity": {"id": "10026713294", "name": "Nintendo"}}, {"domain": {"id": "115", "name": "Video Game Conference", "description": "Video game conferences, like E3"}, "entity": {"id": "1389596244444540928", "name": "E3 2021"}}, {"domain": {"id": "115", "name": "Video Game Conference", "description": "Video game conferences, like E3"}, "entity": {"id": "1399745310889447427", "name": "E3 2021"}}, {"domain": {"id": "79", "name": "Video Game Hardware", "description": "Video Game Hardware"}, "entity": {"id": "856739783577554949", "name": "Nintendo Switch", "description": "Nintendo Switch"}}, {"domain": {"id": "115", "name": "Video Game Conference", "description": "Video game conferences, like E3"}, "entity": {"id": "1389596244444540928", "name": "E3 2021"}}], "text": "Custom Robo or StarFox 100%.  Robo was a wonderful game and I could absolutely see it today as a great multiplayer game.  StarFox has so many places it could go and nintendo shouldn't let that go.\n\n#E32021 \n#NintendoSwitch \n#hopesanddreams\nQuote Tweet https://t.co/hRRAbWwqjD"}, "includes": {"users": [{"name": "Emissaries Of Chaos", "public_metrics": {"followers_count": 2, "following_count": 34, "tweet_count": 5, "listed_count": 0}, "id": "1400682891512729603", "description": "", "username": "EmissariesC", "protected": false, "created_at": "2021-06-04T05:17:17.000Z", "verified": false}]}, "matching_rules": [{"id": 1401668264036548617, "tag": "Fraude - Monterrey, Nuevo Le\u00f3n"}, {"id": 1401668264036548613, "tag": "Fraude - Nuevo Le\u00f3n"}]}