{"data": {"id": "1401695787478835201", "entities": {"annotations": [{"start": 0, "end": 3, "probability": 0.5045, "type": "Person", "normalized_text": "Lima"}, {"start": 36, "end": 39, "probability": 0.4974, "type": "Organization", "normalized_text": "Per\u00fa"}], "urls": [{"start": 41, "end": 64, "url": "https://t.co/DgfuKiApil", "expanded_url": "https://twitter.com/sbelitas/status/1401695654745939974", "display_url": "twitter.com/sbelitas/statu\u2026"}]}, "referenced_tweets": [{"type": "quoted", "id": "1401695654745939974"}], "public_metrics": {"retweet_count": 0, "reply_count": 0, "like_count": 0, "quote_count": 0}, "author_id": "941983980", "created_at": "2021-06-07T00:21:32.000Z", "source": "Twitter for Android", "text": "Lima y tres regiones m\u00e1s vs todo el Per\u00fa https://t.co/DgfuKiApil"}, "includes": {"users": [{"name": "Rz ManuFlopper\u26a1", "public_metrics": {"followers_count": 279, "following_count": 249, "tweet_count": 3828, "listed_count": 0}, "id": "941983980", "description": "\ud83c\uddf5\ud83c\uddea| Novia: \n@PulacheMariana\n\u2764\ufe0f |Player for \n@Razors_Esports\n\u26a1| Manager: \n@Espinosatumbado\n\ud83d\udcdd| Twitch Afiliado\ud83d\udc9c", "username": "ManuFlopper", "protected": false, "created_at": "2012-11-11T19:08:13.000Z", "verified": false}]}, "matching_rules": [{"id": 1401668264036548615, "tag": "Nuevo Le\u00f3n"}, {"id": 1401668264036548614, "tag": "Monterrey"}]}