{"data": {"id": "1401698594021851139", "attachments": {"media_keys": ["3_1401697751663104002"]}, "entities": {"urls": [{"start": 66, "end": 89, "url": "https://t.co/zJUOiMEI8l", "expanded_url": "https://twitter.com/lbrendacastillo/status/1401698594021851139/photo/1", "display_url": "pic.twitter.com/zJUOiMEI8l"}], "hashtags": [{"start": 28, "end": 43, "tag": "Elecciones2021"}, {"start": 44, "end": 65, "tag": "EleccionesM\u00e9xico2021"}]}, "public_metrics": {"retweet_count": 0, "reply_count": 0, "like_count": 0, "quote_count": 0}, "author_id": "1398870596", "created_at": "2021-06-07T00:32:41.000Z", "source": "Twitter Web App", "text": "Ejerciendo la democracia\ud83d\ude18\ud83d\udce5\u2764\n#Elecciones2021 #EleccionesM\u00e9xico2021 https://t.co/zJUOiMEI8l"}, "includes": {"users": [{"name": "Brenda Castillo", "public_metrics": {"followers_count": 40, "following_count": 22, "tweet_count": 32, "listed_count": 0}, "id": "1398870596", "location": "M\u00e9xico", "description": "Destroza tus l\u00edmites\ud83d\udca5\ud83d\udd1d", "username": "lbrendacastillo", "protected": false, "created_at": "2013-05-03T04:53:23.000Z", "verified": false}]}, "matching_rules": [{"id": 1401668264036548615, "tag": "Nuevo Le\u00f3n"}, {"id": 1401668264036548614, "tag": "Monterrey"}]}