{"data": {"entities": {"annotations": [{"start": 112, "end": 117, "probability": 0.9415, "type": "Person", "normalized_text": "Adri\u00e1n"}, {"start": 123, "end": 125, "probability": 0.8125, "type": "Organization", "normalized_text": "PRI"}], "mentions": [{"start": 3, "end": 16, "username": "FestivalChin"}, {"start": 51, "end": 63, "username": "MarkoCortes"}, {"start": 68, "end": 84, "username": "FerLarrazabalNL"}]}, "public_metrics": {"retweet_count": 32, "reply_count": 0, "like_count": 0, "quote_count": 0}, "source": "Twitter for Android", "author_id": "134702154", "created_at": "2021-05-30T16:56:26.000Z", "referenced_tweets": [{"type": "retweeted", "id": "1398880137228304385"}], "text": "RT @FestivalChin: Por favor pasen aqu\u00ed a pedirle a @MarkoCortes y a @FerLarrazabalNL que declinen para que gane Adri\u00e1n del PRI\n\nDebe ganar\u2026", "id": "1399047057294385153"}, "includes": {"users": [{"name": "luis armas", "id": "134702154", "public_metrics": {"followers_count": 38, "following_count": 194, "tweet_count": 3133, "listed_count": 0}, "created_at": "2010-04-19T06:02:44.000Z", "protected": false, "username": "luisarmasr", "description": "", "verified": false}]}, "matching_rules": [{"id": 1399037118148759556, "tag": "Fernando Larrazabal"}]}