{"data": {"id": "1401699364062613510", "entities": {"annotations": [{"start": 29, "end": 31, "probability": 0.6253, "type": "Organization", "normalized_text": "PAN"}, {"start": 54, "end": 56, "probability": 0.9438, "type": "Organization", "normalized_text": "PRI"}, {"start": 102, "end": 110, "probability": 0.6747, "type": "Place", "normalized_text": "Zacatecas"}, {"start": 113, "end": 121, "probability": 0.8736, "type": "Place", "normalized_text": "Michoac\u00e1n"}, {"start": 124, "end": 131, "probability": 0.7702, "type": "Person", "normalized_text": "Guerrero"}, {"start": 135, "end": 140, "probability": 0.9149, "type": "Place", "normalized_text": "Colima"}], "urls": [{"start": 200, "end": 223, "url": "https://t.co/KzYR4x8TdL", "expanded_url": "https://twitter.com/laoctavadigital/status/1401699364062613510/video/1", "display_url": "pic.twitter.com/KzYR4x8TdL"}], "hashtags": [{"start": 0, "end": 15, "tag": "Elecciones2021"}], "mentions": [{"start": 76, "end": 89, "username": "alitomorenoc"}]}, "referenced_tweets": [{"type": "replied_to", "id": "1401699316994093059"}], "attachments": {"media_keys": ["7_1401698491873824769"]}, "public_metrics": {"retweet_count": 0, "reply_count": 0, "like_count": 0, "quote_count": 0}, "in_reply_to_user_id": "164337327", "author_id": "164337327", "created_at": "2021-06-07T00:35:45.000Z", "source": "Twitter Web App", "text": "#Elecciones2021 | Y, como el PAN va en alianza con el PRI, el l\u00edder priista @alitomorenoc asegur\u00f3 que Zacatecas, Michoac\u00e1n, Guerrero y Colima, van en \u201cempates\u201d cerrados para ganar estas gubernaturas. https://t.co/KzYR4x8TdL"}, "includes": {"users": [{"name": "LA OCTAVA", "public_metrics": {"followers_count": 118242, "following_count": 50, "tweet_count": 103945, "listed_count": 543}, "id": "164337327", "location": "M\u00e9xico, D.F", "description": "PERIODISMO Y CREDIBILIDAD\nVe nuestra transmisi\u00f3n EN VIVO en https://t.co/hQw1eUFTby", "username": "laoctavadigital", "protected": false, "created_at": "2010-07-08T16:41:16.000Z", "verified": false}]}, "matching_rules": [{"id": 1401668264036548615, "tag": "Nuevo Le\u00f3n"}, {"id": 1401668264036548614, "tag": "Monterrey"}]}