{"data": {"id": "1401700321882251264", "referenced_tweets": [{"type": "quoted", "id": "1401685669139959810"}], "entities": {"urls": [{"start": 47, "end": 70, "url": "https://t.co/w1BvSt8LOa", "expanded_url": "https://twitter.com/staboadamx/status/1401685669139959810", "display_url": "twitter.com/staboadamx/sta\u2026"}]}, "public_metrics": {"retweet_count": 0, "reply_count": 0, "like_count": 0, "quote_count": 0}, "author_id": "219909609", "created_at": "2021-06-07T00:39:33.000Z", "source": "Twitter for iPhone", "text": "Esperemos que cumpla sus propuestas candidato. https://t.co/w1BvSt8LOa"}, "includes": {"users": [{"name": "Pandemic Spine", "public_metrics": {"followers_count": 509, "following_count": 1107, "tweet_count": 6604, "listed_count": 4}, "id": "219909609", "location": "CDMX, antes Defectuoso", "description": "Surgeon (General, GI y Colorectal) / Cafrepolitano / Gamer / Padre y esposo feliz. Se respeta a todos, pero se manda a chingar a su madre f\u00e1cilmente.", "username": "Luis_Spine", "protected": false, "created_at": "2010-11-26T06:48:39.000Z", "verified": false}]}, "matching_rules": [{"id": 1401668264036548615, "tag": "Nuevo Le\u00f3n"}, {"id": 1401668264036548614, "tag": "Monterrey"}]}