{"data": {"id": "1401701504600379400", "entities": {"annotations": [{"start": 65, "end": 85, "probability": 0.3289, "type": "Organization", "normalized_text": "Alcald\u00eda de Monterrey"}, {"start": 113, "end": 137, "probability": 0.7958, "type": "Place", "normalized_text": "Colonia Pedregal La Silla"}], "mentions": [{"start": 3, "end": 11, "username": "elnorte"}]}, "referenced_tweets": [{"type": "retweeted", "id": "1401700554443792394"}], "public_metrics": {"retweet_count": 9, "reply_count": 0, "like_count": 0, "quote_count": 0}, "author_id": "87014535", "created_at": "2021-06-07T00:44:15.000Z", "source": "Twitter Web App", "text": "RT @elnorte: Un grupo de j\u00f3venes roba una urna con votos para la Alcald\u00eda de Monterrey en la casilla 1416, en la Colonia Pedregal La Silla.\u2026"}, "includes": {"users": [{"name": "viezma", "public_metrics": {"followers_count": 168, "following_count": 89, "tweet_count": 82224, "listed_count": 13}, "id": "87014535", "location": "Cerca de Monterrey", "description": "Me encanta la comunicacion en todas sus formas", "username": "viezma", "protected": false, "created_at": "2009-11-02T19:57:55.000Z", "verified": false}]}, "matching_rules": [{"id": 1401668264036548615, "tag": "Nuevo Le\u00f3n"}, {"id": 1401668264036548614, "tag": "Monterrey"}]}