{"data": {"id": "1401702155468382214", "referenced_tweets": [{"type": "quoted", "id": "1401457598520606722"}], "entities": {"urls": [{"start": 34, "end": 57, "url": "https://t.co/t5WUSqw9vh", "expanded_url": "https://twitter.com/babywithagunx/status/1401457598520606722", "display_url": "twitter.com/babywithagunx/\u2026"}]}, "public_metrics": {"retweet_count": 0, "reply_count": 0, "like_count": 0, "quote_count": 0}, "author_id": "99188918", "created_at": "2021-06-07T00:46:50.000Z", "source": "Twitter for iPhone", "text": "Que coraje , muertos de hambre \ud83d\ude21. https://t.co/t5WUSqw9vh"}, "includes": {"users": [{"name": "\ud835\udc0b\ud835\udc1a\ud835\udc1d\ud835\udc32 \ud835\udc03", "public_metrics": {"followers_count": 583, "following_count": 490, "tweet_count": 44103, "listed_count": 2}, "id": "99188918", "location": "Mazatlan sinaloa", "description": "Veintis\u00e9is. Uno atrae lo que es, no lo que ser\u00e1.", "username": "dianairt", "protected": false, "created_at": "2009-12-24T23:55:16.000Z", "verified": false}]}, "matching_rules": [{"id": 1401668264036548615, "tag": "Nuevo Le\u00f3n"}, {"id": 1401668264036548614, "tag": "Monterrey"}]}