{"data": {"id": "1401703125094965248", "entities": {"annotations": [{"start": 26, "end": 28, "probability": 0.9568, "type": "Organization", "normalized_text": "JNE"}, {"start": 120, "end": 121, "probability": 0.7179, "type": "Organization", "normalized_text": "KK"}], "mentions": [{"start": 0, "end": 12, "username": "dsalaverryv"}]}, "referenced_tweets": [{"type": "replied_to", "id": "1401692921544515587"}], "public_metrics": {"retweet_count": 0, "reply_count": 0, "like_count": 0, "quote_count": 0}, "in_reply_to_user_id": "725011475903950848", "author_id": "939555571321237504", "created_at": "2021-06-07T00:50:42.000Z", "source": "Twitter for Android", "text": "@dsalaverryv Ojal\u00e1 que el JNE no se someta alas presiones de los medios del asco para que se consolidar el fraude de la KK."}, "includes": {"users": [{"name": "Alfredo Navarro", "public_metrics": {"followers_count": 64, "following_count": 355, "tweet_count": 1191, "listed_count": 0}, "id": "939555571321237504", "location": "Jesus Maria Lima", "description": "", "username": "Alfredo17nv", "protected": false, "created_at": "2017-12-09T18:01:19.000Z", "verified": false}]}, "matching_rules": [{"id": 1401668264036548617, "tag": "Fraude - Monterrey, Nuevo Le\u00f3n"}, {"id": 1401668264036548613, "tag": "Fraude - Nuevo Le\u00f3n"}]}