{"data": {"id": "1401705051677245441", "attachments": {"media_keys": ["3_1401705048447590400"]}, "entities": {"urls": [{"start": 87, "end": 110, "url": "https://t.co/9CyWmfMWCe", "expanded_url": "https://twitter.com/IrisAdrianaQM/status/1401705051677245441/photo/1", "display_url": "pic.twitter.com/9CyWmfMWCe"}], "hashtags": [{"start": 71, "end": 86, "tag": "Elecciones2021"}]}, "public_metrics": {"retweet_count": 0, "reply_count": 0, "like_count": 0, "quote_count": 0}, "author_id": "215043841", "created_at": "2021-06-07T00:58:21.000Z", "source": "Twitter for Android", "text": "Cumplimos. Ejercimos nuestro derecho al voto. Y ahora que nos cumplan. #Elecciones2021 https://t.co/9CyWmfMWCe"}, "includes": {"users": [{"name": "Iris Adriana Q.M.", "public_metrics": {"followers_count": 203, "following_count": 200, "tweet_count": 3253, "listed_count": 1}, "id": "215043841", "location": "Quer\u00e9taro", "description": "", "username": "IrisAdrianaQM", "protected": false, "created_at": "2010-11-12T21:26:13.000Z", "verified": false}]}, "matching_rules": [{"id": 1401668264036548615, "tag": "Nuevo Le\u00f3n"}, {"id": 1401668264036548614, "tag": "Monterrey"}]}