{"data": {"id": "1401706057819471880", "entities": {"annotations": [{"start": 63, "end": 68, "probability": 0.7455, "type": "Place", "normalized_text": "mexico"}], "mentions": [{"start": 3, "end": 13, "username": "edgargali"}, {"start": 15, "end": 28, "username": "ChumelTorres"}, {"start": 109, "end": 119, "username": "INEMexico"}]}, "referenced_tweets": [{"type": "retweeted", "id": "1401644355979464710"}], "public_metrics": {"retweet_count": 5, "reply_count": 0, "like_count": 0, "quote_count": 0}, "author_id": "3262752602", "created_at": "2021-06-07T01:02:21.000Z", "source": "Twitter for Android", "context_annotations": [{"domain": {"id": "10", "name": "Person", "description": "Named people in the world like Nelson Mandela"}, "entity": {"id": "1386740562783477761", "name": "Chumel Torres"}}, {"domain": {"id": "119", "name": "Holiday", "description": "Holidays like Christmas or Halloween"}, "entity": {"id": "1286645331686350848", "name": "Dia de la Independencia (Grito de Dolores) ", "description": "This entity includes conversations about Dia de la Independencia (Grito de Dolores) for all years."}}, {"domain": {"id": "120", "name": "Digital Creator", "description": "Influencers who create content on digital platforms"}, "entity": {"id": "1386740562783477761", "name": "Chumel Torres"}}], "text": "RT @edgargali: @ChumelTorres Pero  etiquentelos verguenza para mexico bola de aprovechados come  cuando  hay @INEMexico que castigo  habr\u00e1\u2026"}, "includes": {"users": [{"name": "Humberto Ortega", "public_metrics": {"followers_count": 160, "following_count": 1306, "tweet_count": 17084, "listed_count": 0}, "id": "3262752602", "description": "", "username": "BetortegaHo", "protected": false, "created_at": "2015-07-01T01:56:21.000Z", "verified": false}]}, "matching_rules": [{"id": 1401668264036548616, "tag": "INE - Monterrey"}, {"id": 1401668264036548619, "tag": "INE - Nuevo Le\u00f3n"}]}