{"data": {"id": "1401706889428283397", "referenced_tweets": [{"type": "replied_to", "id": "1401544182360072197"}], "public_metrics": {"retweet_count": 0, "reply_count": 0, "like_count": 0, "quote_count": 0}, "in_reply_to_user_id": "435299501", "author_id": "354683504", "created_at": "2021-06-07T01:05:39.000Z", "source": "Twitter for iPhone", "context_annotations": [{"domain": {"id": "10", "name": "Person", "description": "Named people in the world like Nelson Mandela"}, "entity": {"id": "819535513707126785", "name": "Denise Dresser", "description": "Mexican Political Analyst"}}], "text": "@DeniseDresserG @JuanSan95795346 @INEMexico Y creo que es el momento de volver a alzar la voz,exigir que cualquier representante del gobierno cuente con el perfil requerido para su puesto. Basta de ridiculizar la pol\u00edtica con coreograf\u00edas y strippers. Quiero un gobierno serio, lo merecemos", "entities": {"mentions": [{"start": 0, "end": 15, "username": "DeniseDresserG"}, {"start": 16, "end": 32, "username": "JuanSan95795346"}, {"start": 33, "end": 43, "username": "INEMexico"}]}}, "includes": {"users": [{"name": "Alma Galindo", "public_metrics": {"followers_count": 86, "following_count": 331, "tweet_count": 234, "listed_count": 0}, "id": "354683504", "description": "", "username": "ar_galindo", "protected": false, "created_at": "2011-08-14T03:54:47.000Z", "verified": false}]}, "matching_rules": [{"id": 1401668264036548616, "tag": "INE - Monterrey"}, {"id": 1401668264036548619, "tag": "INE - Nuevo Le\u00f3n"}]}