{"data": {"id": "1401708360228118534", "referenced_tweets": [{"type": "retweeted", "id": "1401707929057771522"}], "public_metrics": {"retweet_count": 15, "reply_count": 0, "like_count": 0, "quote_count": 0}, "author_id": "96024934", "created_at": "2021-06-07T01:11:30.000Z", "source": "Twitter for Android", "text": "RT @vesdape: Un fraude sin la rapidez de la comunicaci\u00f3n hoy en d\u00eda ser\u00eda m\u00e1s sencillo, confiemos y estemos vigilantes, si hay algo que inf\u2026", "entities": {"mentions": [{"start": 3, "end": 11, "username": "vesdape"}]}}, "includes": {"users": [{"name": "Ana Paula", "public_metrics": {"followers_count": 1095, "following_count": 894, "tweet_count": 45938, "listed_count": 4}, "id": "96024934", "location": "Lyon, France", "description": "Bailarina por pasi\u00f3n y Comunicadora por vocaci\u00f3n.", "username": "anapazz", "protected": false, "created_at": "2009-12-11T01:03:32.000Z", "verified": false}]}, "matching_rules": [{"id": 1401668264036548617, "tag": "Fraude - Monterrey, Nuevo Le\u00f3n"}, {"id": 1401668264036548613, "tag": "Fraude - Nuevo Le\u00f3n"}]}