{"data": {"id": "1401709268689211394", "referenced_tweets": [{"type": "retweeted", "id": "1401697671677677568"}], "public_metrics": {"retweet_count": 271, "reply_count": 0, "like_count": 0, "quote_count": 0}, "author_id": "1048781607929143297", "created_at": "2021-06-07T01:15:06.000Z", "source": "Twitter for Android", "text": "RT @MaxKaiser75: Estamos contando votos en mi casilla.....al rato les platico\ud83d\ude0e", "entities": {"mentions": [{"start": 3, "end": 15, "username": "MaxKaiser75"}]}}, "includes": {"users": [{"name": "Armando Montes de Oca Santana", "public_metrics": {"followers_count": 616, "following_count": 650, "tweet_count": 13544, "listed_count": 0}, "id": "1048781607929143297", "description": "", "username": "ArmandoMontesd9", "protected": false, "created_at": "2018-10-07T03:46:35.000Z", "verified": false}]}, "matching_rules": [{"id": 1401668264036548615, "tag": "Nuevo Le\u00f3n"}, {"id": 1401668264036548614, "tag": "Monterrey"}]}