{"data": {"entities": {"annotations": [{"start": 92, "end": 101, "probability": 0.9027, "type": "Place", "normalized_text": "Nuevo Le\u00f3n"}], "mentions": [{"start": 3, "end": 17, "username": "BlancoGeneral"}, {"start": 53, "end": 65, "username": "MarkoCortes"}]}, "public_metrics": {"retweet_count": 14, "reply_count": 0, "like_count": 0, "quote_count": 0}, "source": "Twitter for Android", "context_annotations": [{"domain": {"id": "12", "name": "Sports Team", "description": "A sports team organization, like Arsenal and the Boston Celtics"}, "entity": {"id": "731226230997934083", "name": "Leon"}}], "author_id": "1358598355493003264", "created_at": "2021-05-30T19:46:36.000Z", "referenced_tweets": [{"type": "retweeted", "id": "1399056554238873606"}], "text": "RT @BlancoGeneral: Precisamente a esto quer\u00eda llegar @MarkoCortes, al no ir en coalici\u00f3n en Nuevo Le\u00f3n.\n\nLe est\u00e1 haciendo el juego al Viejo\u2026", "id": "1399089883768135681"}, "includes": {"users": [{"name": "pincheviajero", "id": "1358598355493003264", "public_metrics": {"followers_count": 218, "following_count": 322, "tweet_count": 1947, "listed_count": 0}, "created_at": "2021-02-08T02:07:55.000Z", "protected": false, "username": "elviejitoviajer", "description": "Puedo resistir todo menos la tentaci\u00f3n (Oscar Wilde).\nEst\u00e1 es mi cuenta alterna aqui soy todo lo que haya no soy.  Sin complicaciones", "verified": false}]}, "matching_rules": [{"id": 1399037118148759556, "tag": "Fernando Larrazabal"}]}