{"data": {"id": "1401714042591485957", "entities": {"annotations": [{"start": 75, "end": 79, "probability": 0.6682, "type": "Organization", "normalized_text": "SEGOB"}, {"start": 171, "end": 185, "probability": 0.9783, "type": "Person", "normalized_text": "Manuel Bartlett"}], "urls": [{"start": 188, "end": 211, "url": "https://t.co/PjdG7kSX9s", "expanded_url": "https://twitter.com/Pablo_Hdez/status/1401544240954589189", "display_url": "twitter.com/Pablo_Hdez/sta\u2026"}]}, "referenced_tweets": [{"type": "quoted", "id": "1401544240954589189"}], "public_metrics": {"retweet_count": 0, "reply_count": 0, "like_count": 0, "quote_count": 0}, "author_id": "13001602", "created_at": "2021-06-07T01:34:04.000Z", "source": "Tweetbot for i\u039fS", "text": "Esto\n\nSolo les recuerdo que el mayor fraude electoral del siglo XX lo hizo SEGOB con un retraso electoral de resultados conocido como la ca\u00edda del sistema\n\nOrquestado por Manuel Bartlett. https://t.co/PjdG7kSX9s"}, "includes": {"users": [{"name": "GONZALO OLIVEROS", "public_metrics": {"followers_count": 214833, "following_count": 1985, "tweet_count": 151900, "listed_count": 1162}, "id": "13001602", "location": "M\u00e9xico", "description": "https://t.co/dbkRbx9qUF lunes a viernes a las 8:30.", "username": "goliveros", "protected": false, "created_at": "2008-02-03T05:58:22.000Z", "verified": false}]}, "matching_rules": [{"id": 1401668264036548617, "tag": "Fraude - Monterrey, Nuevo Le\u00f3n"}, {"id": 1401668264036548613, "tag": "Fraude - Nuevo Le\u00f3n"}]}