{"data": {"created_at": "2021-06-07T20:50:01.000Z", "source": "Twitter for iPhone", "author_id": "1329209582921658369", "public_metrics": {"retweet_count": 862, "reply_count": 0, "like_count": 0, "quote_count": 0}, "referenced_tweets": [{"type": "retweeted", "id": "1401898723332984833"}], "entities": {"mentions": [{"start": 3, "end": 15, "username": "alvarosarco"}, {"start": 24, "end": 38, "username": "KeikoFujimori"}]}, "id": "1402004945465974786", "text": "RT @alvarosarco: Se\u00f1ora @KeikoFujimori, deje el papel de buenita y salga a defender con energ\u00eda su voto o le volver\u00e1n a robar las eleccione\u2026"}, "includes": {"users": [{"created_at": "2020-11-18T23:47:20.000Z", "verified": false, "protected": false, "id": "1329209582921658369", "description": "S\u00edganme y compartan para mas contenido , Anti caviar , Anti comunista , Anti aborto  , Anti LTGBIQ , Anti Feminazis.", "public_metrics": {"followers_count": 190, "following_count": 14, "tweet_count": 5827, "listed_count": 0}, "username": "Trollrepublikno", "name": "Troll Republicano"}]}, "matching_rules": [{"id": 1401997773927559174, "tag": "Monterrey"}, {"id": 1401997773927559168, "tag": "Nuevo Le\u00f3n"}]}