{"data": {"created_at": "2021-06-07T20:58:08.000Z", "source": "Twitter for Android", "author_id": "1277080867903614983", "public_metrics": {"retweet_count": 1, "reply_count": 0, "like_count": 0, "quote_count": 0}, "referenced_tweets": [{"type": "retweeted", "id": "1401993172331421707"}], "entities": {"mentions": [{"start": 3, "end": 19, "username": "ElApndicdeGiaco"}, {"start": 21, "end": 31, "username": "my_biglie"}, {"start": 32, "end": 48, "username": "JovenesKonKeiko"}]}, "id": "1402006989505445891", "text": "RT @ElApndicdeGiaco: @my_biglie @JovenesKonKeiko A diferencia de ustedes, cuando gane castillo nosotros no nos vamos a comportar como DELIN\u2026"}, "includes": {"users": [{"created_at": "2020-06-28T03:26:40.000Z", "location": "Lima, Peru", "verified": false, "protected": false, "id": "1277080867903614983", "description": "#SIGUEMEYTESIGO \n#TeamFollowBack \nfan account", "public_metrics": {"followers_count": 859, "following_count": 910, "tweet_count": 3105, "listed_count": 0}, "username": "Andrea17304", "name": "SIGUEMEYTESIGO"}]}, "matching_rules": [{"id": 1401997773927559172, "tag": "Fraude - Monterrey, Nuevo Le\u00f3n"}, {"id": 1401997773927559170, "tag": "Fraude - Nuevo Le\u00f3n"}]}