{"data": {"id": "1401672748007452674", "referenced_tweets": [{"type": "retweeted", "id": "1401664051831263243"}], "attachments": {"media_keys": ["3_1401664049662861313"]}, "entities": {"urls": [{"start": 37, "end": 60, "url": "https://t.co/ypft7lwEOS", "expanded_url": "https://twitter.com/LaLicenciadaP/status/1401664051831263243/photo/1", "display_url": "pic.twitter.com/ypft7lwEOS"}], "mentions": [{"start": 3, "end": 17, "username": "LaLicenciadaP"}]}, "public_metrics": {"retweet_count": 15, "reply_count": 0, "like_count": 0, "quote_count": 0}, "author_id": "273789599", "created_at": "2021-06-06T22:49:59.000Z", "source": "Twitter for Android", "text": "RT @LaLicenciadaP: Yo en la casilla: https://t.co/ypft7lwEOS"}, "includes": {"users": [{"name": "Acta Non Verba \ud83c\udf52 \u27b5\u2661\ud83c\uddf2\ud83c\uddfd", "public_metrics": {"followers_count": 1296, "following_count": 386, "tweet_count": 383293, "listed_count": 63}, "id": "273789599", "location": "M\u00c9XICO", "description": "\u2018fan account\u2019\u27b5\ud83c\udf52\ud83e\udd0e\n#DakotaJohnson\ud83d\udc51#Dakoholic\ud83e\udd84\u221e\u27b5 RBD Lily Collins \ud83d\udc9b ChrisEvans \ud83d\udc9a GiulioBerruti\ud83d\udc97 Blanca Su\u00e1rez \ud83d\udda4SG\ud83d\udc9cTS\ud83e\udd0d\n\n\nAll my love D\ud83d\udc99", "username": "liissett_", "protected": false, "created_at": "2011-03-29T04:57:32.000Z", "verified": false}]}, "matching_rules": [{"id": 1401668264036548615, "tag": "Nuevo Le\u00f3n"}, {"id": 1401668264036548614, "tag": "Monterrey"}]}