{"data": {"attachments": {"media_keys": ["3_1399127590795763716"]}, "referenced_tweets": [{"type": "replied_to", "id": "1399100912291909635"}], "entities": {"urls": [{"start": 52, "end": 75, "url": "https://t.co/kHFqNdsuwV", "expanded_url": "https://twitter.com/Miranda_V0/status/1399127593543106560/photo/1", "display_url": "pic.twitter.com/kHFqNdsuwV"}], "mentions": [{"start": 0, "end": 15, "username": "samuel_garcias"}]}, "public_metrics": {"retweet_count": 0, "reply_count": 0, "like_count": 0, "quote_count": 0}, "created_at": "2021-05-30T22:16:27.000Z", "text": "@samuel_garcias Ya empez\u00f3 y ya acab\u00f3 yo creo jajaja https://t.co/kHFqNdsuwV", "id": "1399127593543106560", "source": "Twitter for iPhone", "in_reply_to_user_id": "258973851", "author_id": "1392501816076783618"}, "includes": {"users": [{"created_at": "2021-05-12T15:28:20.000Z", "verified": false, "protected": false, "public_metrics": {"followers_count": 137, "following_count": 312, "tweet_count": 817, "listed_count": 0}, "id": "1392501816076783618", "name": "Miranda Valdez", "description": "10.07.2013 \ud83e\udd70\u2764\ufe0f", "username": "Miranda_V0"}]}, "matching_rules": [{"id": 1399114301626064897, "tag": "Samuel Garcia"}]}