{"data": {"referenced_tweets": [{"type": "replied_to", "id": "1399182598597922819"}], "public_metrics": {"retweet_count": 0, "reply_count": 0, "like_count": 0, "quote_count": 0}, "created_at": "2021-05-31T02:00:37.000Z", "text": "@MiguelA00108369 @orgullorayado @Israelbarronm @elnorte @samuel_garcias @claraluzflores @FerLarrazabalNL Es algo que no entienden. La elecci\u00f3n es una comedia.\nTenemos a 3 hijos de puta siendo candidatos y a un pinche sanpetrino. Y prefiero al ponche sampetrino que a los otros 3 hijos de puta", "id": "1399184005996716032", "source": "Twitter for Android", "in_reply_to_user_id": "1162396630399799296", "author_id": "1202720468115083266", "entities": {"mentions": [{"start": 0, "end": 16, "username": "MiguelA00108369"}, {"start": 17, "end": 31, "username": "orgullorayado"}, {"start": 32, "end": 46, "username": "Israelbarronm"}, {"start": 47, "end": 55, "username": "elnorte"}, {"start": 56, "end": 71, "username": "samuel_garcias"}, {"start": 72, "end": 87, "username": "claraluzflores"}, {"start": 88, "end": 104, "username": "FerLarrazabalNL"}]}}, "includes": {"users": [{"created_at": "2019-12-05T22:44:45.000Z", "verified": false, "protected": false, "public_metrics": {"followers_count": 32, "following_count": 137, "tweet_count": 4076, "listed_count": 0}, "id": "1202720468115083266", "name": "botlibertario90", "description": "Un bot libertario. le gusta la libertad y la capacidad ganarse la vida honradamente. \ncu\u00eddate de marxistas y feministas. ambos te quieren abajo y sumiso", "username": "Botlibertario45"}]}, "matching_rules": [{"id": 1399183738236461058, "tag": "Samuel Garcia"}, {"id": 1399183738236461056, "tag": "Fernando Larrazabal"}, {"id": 1399183738236461057, "tag": "Clara Luz"}]}