{"data": {"referenced_tweets": [{"type": "replied_to", "id": "1399055009132597248"}], "public_metrics": {"retweet_count": 0, "reply_count": 0, "like_count": 0, "quote_count": 0}, "created_at": "2021-05-31T14:30:41.000Z", "text": "@svegaf @samuel_garcias Samuel no le interesa el pa\u00eds solo su caprichoso de jugar al Gober. Necesitamos alguien serio que represente los intereses del estado .", "id": "1399372769255637001", "source": "Twitter for iPhone", "in_reply_to_user_id": "405567361", "entities": {"annotations": [{"start": 24, "end": 29, "probability": 0.9871, "type": "Person", "normalized_text": "Samuel"}], "mentions": [{"start": 0, "end": 7, "username": "svegaf"}, {"start": 8, "end": 23, "username": "samuel_garcias"}]}, "author_id": "1311254348869955586"}, "includes": {"users": [{"created_at": "2020-09-30T10:39:48.000Z", "verified": false, "protected": false, "location": "Regio", "public_metrics": {"followers_count": 123, "following_count": 202, "tweet_count": 4439, "listed_count": 0}, "id": "1311254348869955586", "name": "Luis G Garcia", "description": "Chemical Engineer \ud83d\udc77\u200d\u2642\ufe0f #\ud835\udd0f\ud835\udd26\ud835\udd24\ud835\udd1e\ud835\udd07\ud835\udd22\ud835\udd0a\ud835\udd32\ud835\udd22\ud835\udd2f\ud835\udd2f\ud835\udd22\ud835\udd2f\ud835\udd2c\ud835\udd30", "username": "LuisGGa03017827"}]}, "matching_rules": [{"id": 1399348810183327754, "tag": "Samuel Garcia"}]}