{"data": {"id": "1401675962031431682", "entities": {"annotations": [{"start": 83, "end": 86, "probability": 0.8559, "type": "Place", "normalized_text": "Per\u00fa"}], "hashtags": [{"start": 108, "end": 131, "tag": "EleccionesBicentenario"}], "mentions": [{"start": 3, "end": 15, "username": "GermanLoero"}]}, "referenced_tweets": [{"type": "retweeted", "id": "1401551305567621121"}], "public_metrics": {"retweet_count": 1158, "reply_count": 0, "like_count": 0, "quote_count": 0}, "author_id": "1010991215091863552", "created_at": "2021-06-06T23:02:45.000Z", "source": "Twitter for Android", "text": "RT @GermanLoero: \u00a1No se abri\u00f3 mi mesa as\u00ed que me ofrec\u00ed de voluntario! Todo por el Per\u00fa\n\u00a1YO NO TENGO MIEDO!\n#EleccionesBicentenario\u00a0 #Elecc\u2026"}, "includes": {"users": [{"name": "Ricardo Bravo", "public_metrics": {"followers_count": 100, "following_count": 198, "tweet_count": 12813, "listed_count": 0}, "id": "1010991215091863552", "description": "", "username": "Ricardo12397889", "protected": false, "created_at": "2018-06-24T21:01:03.000Z", "verified": false}]}, "matching_rules": [{"id": 1401668264036548615, "tag": "Nuevo Le\u00f3n"}, {"id": 1401668264036548614, "tag": "Monterrey"}]}