{"data": {"created_at": "2021-06-06T22:30:58.000Z", "source": "Twitter for Android", "author_id": "2961275565", "public_metrics": {"retweet_count": 0, "reply_count": 0, "like_count": 0, "quote_count": 0}, "entities": {"hashtags": [{"start": 22, "end": 28, "tag": "votar"}, {"start": 52, "end": 66, "tag": "VotaPorMexico"}, {"start": 67, "end": 83, "tag": "VotoInteligente"}, {"start": 84, "end": 103, "tag": "VotarEsDeChingones"}]}, "id": "1401667961677565954", "text": "30 minutos , salgan a #votar vecinos, hay tiempo!!! #VotaPorMexico #VotoInteligente #VotarEsDeChingones"}, "includes": {"users": [{"created_at": "2015-01-05T01:39:06.000Z", "location": "Moctezuma 1 y 2 a seccion", "verified": false, "protected": false, "id": "2961275565", "description": "Aqui puedes plubicar tu negocio de la zona, vender, subir fotos de perros o gatos perdidos de la zona, denunciar. Bienvenidos!!!", "public_metrics": {"followers_count": 1003, "following_count": 2246, "tweet_count": 4554, "listed_count": 3}, "username": "ColMoctezuma", "name": "MoctezumaColonia2a"}]}, "matching_rules": [{"id": 1401667908032417805, "tag": "Monterrey"}, {"id": 1401667908032417806, "tag": "Nuevo Le\u00f3n"}]}