{"data": {"attachments": {"media_keys": ["3_1398811942974738433"]}, "entities": {"mentions": [{"start": 0, "end": 16, "username": "MatiasDomngue16"}, {"start": 17, "end": 32, "username": "samuel_garcias"}], "hashtags": [{"start": 111, "end": 120, "tag": "VotoUtil"}], "urls": [{"start": 145, "end": 168, "url": "https://t.co/2QMyLycoz0", "expanded_url": "https://twitter.com/RodolfoOJE/status/1398811944610668549/photo/1", "display_url": "pic.twitter.com/2QMyLycoz0"}], "annotations": [{"start": 76, "end": 85, "probability": 0.334, "type": "Place", "normalized_text": "Nuevo Le\u00f3n"}]}, "author_id": "1387765553490706444", "in_reply_to_user_id": "1374595093513052160", "referenced_tweets": [{"type": "replied_to", "id": "1398810867202932736"}], "public_metrics": {"retweet_count": 0, "reply_count": 0, "like_count": 0, "quote_count": 0}, "source": "Twitter for Android", "text": "@MatiasDomngue16 @samuel_garcias No permitamos que estos lleguen a gobernar Nuevo Le\u00f3n, hagamos v\u00e1lido nuestro #VotoUtil hay mejores opciones... https://t.co/2QMyLycoz0", "id": "1398811944610668549", "created_at": "2021-05-30T01:22:10.000Z"}, "includes": {"users": [{"created_at": "2021-04-29T13:48:01.000Z", "verified": false, "name": "Rodolfo Ojeda", "username": "RodolfoOJE", "description": "La familia siempre es primero \ud83d\udc6a\u2764\ufe0f", "id": "1387765553490706444", "protected": false, "public_metrics": {"followers_count": 135, "following_count": 287, "tweet_count": 938, "listed_count": 0}}]}, "matching_rules": [{"id": 1398729449777111045, "tag": "Samuel Garcia"}]}