{"data": {"id": "1401677194456412160", "referenced_tweets": [{"type": "retweeted", "id": "1401588848891727880"}], "attachments": {"media_keys": ["3_1401588814854897664"]}, "entities": {"urls": [{"start": 35, "end": 58, "url": "https://t.co/p5ZRJGBc40", "expanded_url": "https://twitter.com/adygarcia72/status/1401588848891727880/photo/1", "display_url": "pic.twitter.com/p5ZRJGBc40"}], "hashtags": [{"start": 19, "end": 34, "tag": "Elecciones2021"}], "mentions": [{"start": 3, "end": 15, "username": "adygarcia72"}]}, "public_metrics": {"retweet_count": 3, "reply_count": 0, "like_count": 0, "quote_count": 0}, "author_id": "2897098558", "created_at": "2021-06-06T23:07:39.000Z", "source": "Twitter for Android", "text": "RT @adygarcia72: \ud83d\udc15 #Elecciones2021 https://t.co/p5ZRJGBc40"}, "includes": {"users": [{"name": "Carlos", "public_metrics": {"followers_count": 55, "following_count": 380, "tweet_count": 2659, "listed_count": 0}, "id": "2897098558", "description": "", "username": "701b7a6ade97414", "protected": false, "created_at": "2014-11-29T08:01:16.000Z", "verified": false}]}, "matching_rules": [{"id": 1401668264036548615, "tag": "Nuevo Le\u00f3n"}, {"id": 1401668264036548614, "tag": "Monterrey"}]}