{"data": {"id": "1401677414925848576", "entities": {"annotations": [{"start": 45, "end": 51, "probability": 0.5198, "type": "Person", "normalized_text": "casilla"}], "urls": [{"start": 143, "end": 166, "url": "https://t.co/N0Ccm4eXDB", "expanded_url": "https://twitter.com/NotLaGrupa/status/1401621037205405701", "display_url": "twitter.com/NotLaGrupa/sta\u2026"}], "mentions": [{"start": 14, "end": 24, "username": "dulcebaez"}]}, "referenced_tweets": [{"type": "quoted", "id": "1401621037205405701"}], "public_metrics": {"retweet_count": 0, "reply_count": 0, "like_count": 0, "quote_count": 0}, "author_id": "271050577", "created_at": "2021-06-06T23:08:32.000Z", "source": "Twitter for Android", "text": "El d\u00eda que la @dulcebaez y yo seamos jefe de casilla, literal va a ser la mejor casilla organizada y m\u00e1s eficaz. INTJs just have it their way. https://t.co/N0Ccm4eXDB"}, "includes": {"users": [{"name": "Degris", "public_metrics": {"followers_count": 193, "following_count": 193, "tweet_count": 18767, "listed_count": 3}, "id": "271050577", "location": "Somewhere in, Mexico", "description": "A full-time retard with an unquenchable thirst for Dr. Pepper.", "username": "elpincheivan", "protected": false, "created_at": "2011-03-23T19:20:59.000Z", "verified": false}]}, "matching_rules": [{"id": 1401668264036548615, "tag": "Nuevo Le\u00f3n"}, {"id": 1401668264036548614, "tag": "Monterrey"}]}