{"data": {"referenced_tweets": [{"type": "quoted", "id": "1399387790639603714"}], "entities": {"urls": [{"start": 45, "end": 68, "url": "https://t.co/lvjJCNEepC", "expanded_url": "https://twitter.com/DJMatus/status/1399387790639603714", "display_url": "twitter.com/DJMatus/status\u2026"}]}, "public_metrics": {"retweet_count": 0, "reply_count": 0, "like_count": 0, "quote_count": 0}, "created_at": "2021-05-31T20:46:41.000Z", "text": "Es que  Le est\u00e1n hechando la mano a morena \ud83d\ude44 https://t.co/lvjJCNEepC", "id": "1399467392523178002", "source": "Twitter for Android", "author_id": "128341894"}, "includes": {"users": [{"created_at": "2010-03-31T21:07:56.000Z", "verified": false, "protected": false, "public_metrics": {"followers_count": 325, "following_count": 324, "tweet_count": 47416, "listed_count": 0}, "id": "128341894", "name": "Angelic", "description": "La tecnolog\u00eda es un siervo \u00fatil... o un amo peligroso.\n                                                          - Christian Lous L.", "username": "lachicabonden3d"}]}, "matching_rules": [{"id": 1399348810183327752, "tag": "Fernando Larrazabal"}]}