{"data": {"id": "1401678176699441154", "referenced_tweets": [{"type": "retweeted", "id": "1401584312605097984"}], "entities": {"hashtags": [{"start": 66, "end": 79, "tag": "6DeJunio2021"}, {"start": 103, "end": 118, "tag": "Elecciones2021"}], "mentions": [{"start": 3, "end": 13, "username": "AriasNora"}]}, "public_metrics": {"retweet_count": 36, "reply_count": 0, "like_count": 0, "quote_count": 0}, "author_id": "1286311345936191489", "created_at": "2021-06-06T23:11:33.000Z", "source": "Twitter for Android", "text": "RT @AriasNora: Hace unos minutos ejerc\u00ed mi derecho al voto. \nEste #6DeJunio2021 es importante tu voto. #Elecciones2021 https://t.co/DBLQm6N\u2026"}, "includes": {"users": [{"name": "mendozzaymendozza", "public_metrics": {"followers_count": 376, "following_count": 391, "tweet_count": 17456, "listed_count": 0}, "id": "1286311345936191489", "location": "Nayarit, M\u00e9xico", "description": "El que ayuda por inter\u00e9s ser\u00e1 astuto m\u00e1s nunca bueno. Marco Tulio Cicer\u00f3n", "username": "sarahmendozzaf", "protected": false, "created_at": "2020-07-23T14:52:00.000Z", "verified": false}]}, "matching_rules": [{"id": 1401668264036548615, "tag": "Nuevo Le\u00f3n"}, {"id": 1401668264036548614, "tag": "Monterrey"}]}