{"data": {"id": "1401679338760806413", "referenced_tweets": [{"type": "retweeted", "id": "1401632444642590720"}], "public_metrics": {"retweet_count": 359, "reply_count": 0, "like_count": 0, "quote_count": 0}, "author_id": "2816200010", "created_at": "2021-06-06T23:16:10.000Z", "source": "Twitter for Android", "text": "RT @EmilioAlvarezI: \u201cNo somos iguales\u201d... dec\u00edan .\n\n@INEMexico \n@FGRMexico", "entities": {"mentions": [{"start": 3, "end": 18, "username": "EmilioAlvarezI"}, {"start": 52, "end": 62, "username": "INEMexico"}, {"start": 64, "end": 74, "username": "FGRMexico"}]}}, "includes": {"users": [{"name": "Riuts Low", "public_metrics": {"followers_count": 88, "following_count": 123, "tweet_count": 3816, "listed_count": 0}, "id": "2816200010", "location": "Mexico, D.F.", "description": "", "username": "riaby22", "protected": false, "created_at": "2014-09-18T03:14:50.000Z", "verified": false}]}, "matching_rules": [{"id": 1401668264036548616, "tag": "INE - Monterrey"}, {"id": 1401668264036548619, "tag": "INE - Nuevo Le\u00f3n"}]}