{"data": {"id": "1401682078689808384", "referenced_tweets": [{"type": "retweeted", "id": "1401681763395686411"}], "entities": {"hashtags": [{"start": 98, "end": 113, "tag": "Elecciones2021"}], "mentions": [{"start": 3, "end": 12, "username": "ixraellg"}]}, "public_metrics": {"retweet_count": 199, "reply_count": 0, "like_count": 0, "quote_count": 0}, "author_id": "229551830", "created_at": "2021-06-06T23:27:04.000Z", "source": "NUDESCSANTA", "text": "RT @ixraellg: Creo que ahora si todas las personas est\u00e1n mandando ALV a MORENA \ud83e\udd1e\ud83c\udffb\ud83e\udd1e\ud83c\udffb\n\nConfirmen. \n\n#Elecciones2021"}, "includes": {"users": [{"name": "GONORREA \u30c5\ud83c\udde8\ud83c\uddf4\u270a\ud83c\udffb", "public_metrics": {"followers_count": 12666, "following_count": 234, "tweet_count": 16732, "listed_count": 34}, "id": "229551830", "location": "Bogot\u00e1, D.C., Colombia", "description": "\ud83c\udd97\ud83d\udc68\ud83c\udffb\u200d\ud83d\udcbb   \n\n\n\n\n\n\ud835\udc9f\ud835\udcbe\ud835\udc52\ud835\udc54\ud835\udc5c \ud835\udc9c\ud835\udcc1\ud835\udc52\ud835\udcbf\ud835\udcb6\ud835\udcc3\ud835\udcb9\ud835\udcc7\ud835\udc5c\ud83e\udd1f\ud83c\udffd", "username": "DIEGO94___", "protected": false, "created_at": "2010-12-22T18:05:41.000Z", "verified": false}]}, "matching_rules": [{"id": 1401668264036548615, "tag": "Nuevo Le\u00f3n"}, {"id": 1401668264036548614, "tag": "Monterrey"}]}