{"data": {"id": "1401669356992536576", "entities": {"annotations": [{"start": 7, "end": 21, "probability": 0.9711, "type": "Place", "normalized_text": "Lomas de Medina"}, {"start": 130, "end": 133, "probability": 0.9567, "type": "Place", "normalized_text": "Le\u00f3n"}], "urls": [{"start": 173, "end": 196, "url": "https://t.co/rzTD9EFUEw", "expanded_url": "https://guanajuato.lasillarota.com/estados/lo-importante-es-ir-a-votar-no-hay-obstaculo-que-lo-impida/526332", "display_url": "guanajuato.lasillarota.com/estados/lo-imp\u2026", "images": [{"url": "https://pbs.twimg.com/news_img/1401665634069401602/ppzEVIXk?format=jpg&name=orig", "width": 480, "height": 345}, {"url": "https://pbs.twimg.com/news_img/1401665634069401602/ppzEVIXk?format=jpg&name=150x150", "width": 150, "height": 150}], "status": 200, "title": "Lo importante es ir a votar: no hay obst\u00e1culo que lo impida", "description": "En Lomas de Medina, en donde no hay pavimentaci\u00f3n ni alumbrado p\u00fablico, los habitantes acuden a las urnas", "unwound_url": "https://guanajuato.lasillarota.com/estados/lo-importante-es-ir-a-votar-no-hay-obstaculo-que-lo-impida/526332"}, {"start": 197, "end": 220, "url": "https://t.co/TdSpqrHaVd", "expanded_url": "https://twitter.com/OrtizIvonne03/status/1401669356992536576/photo/1", "display_url": "pic.twitter.com/TdSpqrHaVd"}, {"start": 197, "end": 220, "url": "https://t.co/TdSpqrHaVd", "expanded_url": "https://twitter.com/OrtizIvonne03/status/1401669356992536576/photo/1", "display_url": "pic.twitter.com/TdSpqrHaVd"}, {"start": 197, "end": 220, "url": "https://t.co/TdSpqrHaVd", "expanded_url": "https://twitter.com/OrtizIvonne03/status/1401669356992536576/photo/1", "display_url": "pic.twitter.com/TdSpqrHaVd"}], "hashtags": [{"start": 135, "end": 150, "tag": "Elecciones2021"}]}, "attachments": {"media_keys": ["3_1401669326357336068", "3_1401669338134990850", "3_1401669354312327170"]}, "public_metrics": {"retweet_count": 0, "reply_count": 0, "like_count": 0, "quote_count": 0}, "author_id": "1106582832250568705", "created_at": "2021-06-06T22:36:31.000Z", "source": "Twitter for Android", "text": "\ud83d\udcf7\ud83d\udc47En Lomas de Medina, en donde no hay pavimentaci\u00f3n ni alumbrado p\u00fablico, los habitantes acuden a las urnas este 6 de junio, en Le\u00f3n.\n\n#Elecciones2021 Mi breve cr\u00f3nica aqu\u00ed\nhttps://t.co/rzTD9EFUEw https://t.co/TdSpqrHaVd"}, "includes": {"users": [{"name": "Ivonne Ortiz", "public_metrics": {"followers_count": 54, "following_count": 169, "tweet_count": 263, "listed_count": 2}, "id": "1106582832250568705", "description": "25 a\u00f1os\nReportera en @LSRGuanajuato. \nMe gusta escuchar y contar historias.\nLe\u00f3n \ud83e\udd8b", "username": "OrtizIvonne03", "protected": false, "created_at": "2019-03-15T15:48:01.000Z", "verified": false}]}, "matching_rules": [{"id": 1401668264036548615, "tag": "Nuevo Le\u00f3n"}, {"id": 1401668264036548614, "tag": "Monterrey"}]}