{"data": {"id": "1401683451376504832", "entities": {"annotations": [{"start": 70, "end": 72, "probability": 0.8986, "type": "Organization", "normalized_text": "AFP"}], "mentions": [{"start": 3, "end": 13, "username": "anamesiac"}]}, "referenced_tweets": [{"type": "retweeted", "id": "1401207078807650306"}], "public_metrics": {"retweet_count": 229, "reply_count": 0, "like_count": 0, "quote_count": 0}, "author_id": "1209210717867577346", "created_at": "2021-06-06T23:32:31.000Z", "source": "Twitter for iPhone", "text": "RT @anamesiac: No dejes que la extrema izquierda te ROBE tu dinero de AFP , es un ROBO aunque le llamen NACIONALIZAR , son dineros particul\u2026"}, "includes": {"users": [{"name": "Colo Colo", "public_metrics": {"followers_count": 347, "following_count": 477, "tweet_count": 13333, "listed_count": 0}, "id": "1209210717867577346", "description": "", "username": "ColoCol56346379", "protected": false, "created_at": "2019-12-23T20:36:21.000Z", "verified": false}]}, "matching_rules": [{"id": 1401668264036548617, "tag": "Fraude - Monterrey, Nuevo Le\u00f3n"}, {"id": 1401668264036548613, "tag": "Fraude - Nuevo Le\u00f3n"}]}