{"data": {"id": "1401687298132086786", "referenced_tweets": [{"type": "quoted", "id": "1401568384744046597"}], "entities": {"urls": [{"start": 32, "end": 55, "url": "https://t.co/scuGlL5Ngx", "expanded_url": "https://twitter.com/garza_onofre/status/1401568384744046597", "display_url": "twitter.com/garza_onofre/s\u2026"}]}, "public_metrics": {"retweet_count": 0, "reply_count": 0, "like_count": 0, "quote_count": 0}, "author_id": "1286835091201757185", "created_at": "2021-06-06T23:47:48.000Z", "source": "Twitter for Android", "text": "Me ven\u00edan siguiendo o que pedo? https://t.co/scuGlL5Ngx"}, "includes": {"users": [{"name": "Edgar", "public_metrics": {"followers_count": 16, "following_count": 155, "tweet_count": 242, "listed_count": 0}, "id": "1286835091201757185", "description": "", "username": "Edfar21823540", "protected": false, "created_at": "2020-07-25T01:26:19.000Z", "verified": false}]}, "matching_rules": [{"id": 1401668264036548615, "tag": "Nuevo Le\u00f3n"}, {"id": 1401668264036548614, "tag": "Monterrey"}]}