{"data": {"id": "1401687447830925317", "referenced_tweets": [{"type": "retweeted", "id": "1401682253168656386"}], "public_metrics": {"retweet_count": 2854, "reply_count": 0, "like_count": 0, "quote_count": 0}, "author_id": "384639296", "created_at": "2021-06-06T23:48:24.000Z", "source": "Twitter for iPhone", "text": "RT @CiroMurayamaINE: Los votos no se han contado.\n\nQuienes en este momento se declaran ganadores son irresponsables.\n\nLa primera informaci\u00f3\u2026", "entities": {"mentions": [{"start": 3, "end": 19, "username": "CiroMurayamaINE"}]}}, "includes": {"users": [{"name": "natalia galvan", "public_metrics": {"followers_count": 409, "following_count": 395, "tweet_count": 6561, "listed_count": 0}, "id": "384639296", "location": "Ci\u00e9nega de Flores, Nuevo Le\u00f3n", "description": "Facultad de Ciencias Quimicas #IIA", "username": "natalia_galvan", "protected": false, "created_at": "2011-10-04T01:54:20.000Z", "verified": false}]}, "matching_rules": [{"id": 1401668264036548616, "tag": "INE - Monterrey"}, {"id": 1401668264036548619, "tag": "INE - Nuevo Le\u00f3n"}]}