{"data": {"id": "1401688519404306434", "referenced_tweets": [{"type": "retweeted", "id": "1401488378097504258"}], "attachments": {"media_keys": ["3_1401488374704361472"]}, "entities": {"urls": [{"start": 79, "end": 102, "url": "https://t.co/TzLwDUcksQ", "expanded_url": "https://twitter.com/linda_dimitrov/status/1401488378097504258/photo/1", "display_url": "pic.twitter.com/TzLwDUcksQ"}], "hashtags": [{"start": 64, "end": 78, "tag": "VotaPorMexico"}], "mentions": [{"start": 3, "end": 18, "username": "linda_dimitrov"}]}, "public_metrics": {"retweet_count": 628, "reply_count": 0, "like_count": 0, "quote_count": 0}, "author_id": "328556620", "created_at": "2021-06-06T23:52:39.000Z", "source": "Twitter for Android", "text": "RT @linda_dimitrov: Para que lo piensen 2 veces antes de votar. #VotaPorMexico https://t.co/TzLwDUcksQ"}, "includes": {"users": [{"name": "\ud83d\udee1\ud83d\udde1\ud83d\udd6f\ud83d\udcdd\ud83d\udcd6Pepe Torres #LigaDeGuereros\ud83d\udee1\ud83d\udde1\ud83d\udd6f\ud83d\udcdd\ud83d\udcd6", "public_metrics": {"followers_count": 3401, "following_count": 5001, "tweet_count": 48819, "listed_count": 9}, "id": "328556620", "location": "MEXICO", "description": "LA VERDAD ES LA VERDAD, PERO QUIEN DIGA YO NO MIENTO, YA LO EST\u00c1 HACIENDO\n\n(NO soy bot, NO soy espam)", "username": "SaTorres7", "protected": false, "created_at": "2011-07-03T16:10:57.000Z", "verified": false}]}, "matching_rules": [{"id": 1401668264036548615, "tag": "Nuevo Le\u00f3n"}, {"id": 1401668264036548614, "tag": "Monterrey"}]}