{"data": {"id": "1401688614019424258", "referenced_tweets": [{"type": "retweeted", "id": "1401636063366553600"}], "public_metrics": {"retweet_count": 4, "reply_count": 0, "like_count": 0, "quote_count": 0}, "author_id": "2386626678", "created_at": "2021-06-06T23:53:02.000Z", "source": "Twitter Web App", "text": "RT @Beatrix_G: Ya se borr\u00f3 la tinta de mi dedo \ud83d\ude44\n@INEMexico", "entities": {"mentions": [{"start": 3, "end": 13, "username": "Beatrix_G"}, {"start": 49, "end": 59, "username": "INEMexico"}]}}, "includes": {"users": [{"name": "Mis ideas son mas chingonas que mi ORTOgrafia \ud83c\uddf2\ud83c\uddfd", "public_metrics": {"followers_count": 27, "following_count": 131, "tweet_count": 10247, "listed_count": 0}, "id": "2386626678", "description": "Obradorista +no morenista \u274cque obradorista es una idea rectora y morenista es una institucion rectora que idea", "username": "Pakito_javive", "protected": false, "created_at": "2014-03-13T08:47:41.000Z", "verified": false}]}, "matching_rules": [{"id": 1401668264036548616, "tag": "INE - Monterrey"}, {"id": 1401668264036548619, "tag": "INE - Nuevo Le\u00f3n"}]}