{"data": {"id": "1401689069701238785", "referenced_tweets": [{"type": "retweeted", "id": "1401606396077084673"}], "public_metrics": {"retweet_count": 424, "reply_count": 0, "like_count": 0, "quote_count": 0}, "author_id": "2857722227", "created_at": "2021-06-06T23:54:50.000Z", "source": "Twitter for Android", "text": "RT @novaeramidia: \ud83c\uddf5\ud83c\uddea | Fraude na elei\u00e7\u00e3o peruana: A pol\u00edcia det\u00e9m um funcion\u00e1rio do partido de extrema-esquerda Peru Libre com c\u00e9dulas elei\u2026", "entities": {"mentions": [{"start": 3, "end": 16, "username": "novaeramidia"}]}}, "includes": {"users": [{"name": "Alexandre Guimar\u00e3es \ud83c\udde7\ud83c\uddf7\ud83c\uddfa\ud83c\uddf2\ud83c\uddf9\ud83c\uddfc\ud83c\uddee\ud83c\uddf1", "public_metrics": {"followers_count": 563, "following_count": 1089, "tweet_count": 55534, "listed_count": 2}, "id": "2857722227", "location": "Estados Unidos", "description": "ac\u00e9falos da esquerda com argumentos toscos \u00e9 block imediato!", "username": "ga70alexandre", "protected": false, "created_at": "2014-11-02T21:54:37.000Z", "verified": false}]}, "matching_rules": [{"id": 1401668264036548617, "tag": "Fraude - Monterrey, Nuevo Le\u00f3n"}, {"id": 1401668264036548613, "tag": "Fraude - Nuevo Le\u00f3n"}]}