{"data": {"id": "1401689905424707585", "referenced_tweets": [{"type": "quoted", "id": "1401671545387466753"}], "entities": {"urls": [{"start": 34, "end": 57, "url": "https://t.co/7wYhwQmVl7", "expanded_url": "https://twitter.com/anvkiin/status/1401671545387466753", "display_url": "twitter.com/anvkiin/status\u2026"}]}, "public_metrics": {"retweet_count": 0, "reply_count": 0, "like_count": 0, "quote_count": 0}, "author_id": "838762857365921792", "created_at": "2021-06-06T23:58:10.000Z", "source": "Twitter for iPhone", "text": "Le coca. F\u00e2chez vous comme voulez https://t.co/7wYhwQmVl7"}, "includes": {"users": [{"name": "\ud83c\udff4\u200d\u2620\ufe0f", "public_metrics": {"followers_count": 161, "following_count": 206, "tweet_count": 36016, "listed_count": 0}, "id": "838762857365921792", "description": "Humble dans mon arrogance \ud83c\uddf8\ud83c\uddf3", "username": "abatlahess76", "protected": false, "created_at": "2017-03-06T14:47:03.000Z", "verified": false}]}, "matching_rules": [{"id": 1401668264036548617, "tag": "Fraude - Monterrey, Nuevo Le\u00f3n"}, {"id": 1401668264036548613, "tag": "Fraude - Nuevo Le\u00f3n"}]}